arrayutilities/__init__.py
tests/__init__.py
tests/test_accessible.py
tests/test_add.py
tests/test_add_prefixed_keys_to.py
tests/test_add_unprefixed_keys_to.py
tests/test_collapse.py
tests/test_dot.py
tests/test_exists.py
tests/test_filter_prefixed.py
tests/test_first.py
tests/test_flatten.py
tests/test_forget.py
tests/test_get.py
tests/test_has.py
tests/test_insert_after_key.py
tests/test_insert_before_key.py
tests/test_is_dict.py
tests/test_is_list.py
tests/test_join.py
tests/test_last.py
tests/test_list_to_dict.py
tests/test_list_to_string.py
tests/test_merge_recursive.py
tests/test_only.py
tests/test_prepend.py
tests/test_pull.py
tests/test_query.py
tests/test_random.py
tests/test_recursive_ksort.py
tests/test_set.py
tests/test_shape_filter.py
tests/test_shuffle.py
tests/test_sort_by_priority.py
tests/test_sort_recursive.py
tests/test_str_to_list.py
tests/test_stringify_keys.py
tests/test_strpos.py
tests/test_undot.py
tests/test_usearch.py
tests/test_visit_recursive.py
tests/test_where.py
tests/test_where_not_none.py
tests/test_wrap.py
arrayutilities-1.1.1.dist-info/LICENSE
arrayutilities-1.1.1.dist-info/METADATA
arrayutilities-1.1.1.dist-info/WHEEL
arrayutilities-1.1.1.dist-info/top_level.txt
arrayutilities-1.1.1.dist-info/RECORD
