Metadata-Version: 2.1
Name: arrayutilities
Version: 1.1.1
Summary: A library for list, dict, and UserDict manipulations.
Author: Matthew Batchelder
Author-email: Matthew Batchelder <borkweb@gmail.com>
License: MIT License
Project-URL: Homepage, https://github.com/borkweb/python-arrayutilities
Keywords: list,dict,UserDict,library
Classifier: License :: OSI Approved :: MIT License
Classifier: Programming Language :: Python
Classifier: Programming Language :: Python :: 3
Requires-Python: >=3.8
License-File: LICENSE
